marklink/__init__.py
marklink/__version__.py
marklink/marklink.py
marklink-1.1.0.dist-info/METADATA
marklink-1.1.0.dist-info/WHEEL
marklink-1.1.0.dist-info/entry_points.txt
marklink-1.1.0.dist-info/RECORD
