Metadata-Version: 2.1
Name: marklink
Version: 1.1.0
Summary: Create markdown links from text containing URLs
License: MIT
Author: Anders K. Pettersen
Author-email: andstatical@gmail.com
Requires-Python: >=3.8.0
Classifier: License :: OSI Approved :: MIT License
Classifier: Programming Language :: Python :: 3
Classifier: Programming Language :: Python :: 3.8
Classifier: Programming Language :: Python :: 3.9
Classifier: Programming Language :: Python :: 3.10
Classifier: Programming Language :: Python :: 3.11
Requires-Dist: beautifulsoup4
Requires-Dist: configargparse
Requires-Dist: lxml
Requires-Dist: requests
